<?xml version="1.0" encoding="UTF-8"?><record_update>
    <sys_ui_section action="DELETE" caption="Statistics" section_id="059c916fa4c350107f44f6612a8fb661" sys_domain="global" table="x_cdltd_loaner_req_loaner_request" version="3" view="ESS">
        <sys_ui_element action="INSERT_OR_UPDATE">
            <element>opened_at</element>
            <position>0</position>
            <sys_created_by>admin</sys_created_by>
            <sys_created_on>2020-09-10 14:01:12</sys_created_on>
            <sys_id>dd9c916fa4c350107f44f6612a8fb67f</sys_id>
            <sys_mod_count>0</sys_mod_count>
            <sys_ui_formatter/>
            <sys_ui_section caption="Statistics" display_value="Statistics" name="x_cdltd_loaner_req_loaner_request" sys_domain="global" view="d02a3041082300107f447452aafab96f">059c916fa4c350107f44f6612a8fb661</sys_ui_section>
            <sys_updated_by>admin</sys_updated_by>
            <sys_updated_on>2020-09-10 14:01:12</sys_updated_on>
            <sys_user/>
            <type/>
        </sys_ui_element>
        <sys_ui_element action="INSERT_OR_UPDATE">
            <element>sys_updated_on</element>
            <position>1</position>
            <sys_created_by>admin</sys_created_by>
            <sys_created_on>2020-09-10 14:01:12</sys_created_on>
            <sys_id>519c916fa4c350107f44f6612a8fb680</sys_id>
            <sys_mod_count>0</sys_mod_count>
            <sys_ui_formatter/>
            <sys_ui_section caption="Statistics" display_value="Statistics" name="x_cdltd_loaner_req_loaner_request" sys_domain="global" view="d02a3041082300107f447452aafab96f">059c916fa4c350107f44f6612a8fb661</sys_ui_section>
            <sys_updated_by>admin</sys_updated_by>
            <sys_updated_on>2020-09-10 14:01:12</sys_updated_on>
            <sys_user/>
            <type/>
        </sys_ui_element>
        <sys_ui_element action="INSERT_OR_UPDATE">
            <element>closed_at</element>
            <position>2</position>
            <sys_created_by>admin</sys_created_by>
            <sys_created_on>2020-09-10 14:01:12</sys_created_on>
            <sys_id>d19c916fa4c350107f44f6612a8fb680</sys_id>
            <sys_mod_count>0</sys_mod_count>
            <sys_ui_formatter/>
            <sys_ui_section caption="Statistics" display_value="Statistics" name="x_cdltd_loaner_req_loaner_request" sys_domain="global" view="d02a3041082300107f447452aafab96f">059c916fa4c350107f44f6612a8fb661</sys_ui_section>
            <sys_updated_by>admin</sys_updated_by>
            <sys_updated_on>2020-09-10 14:01:12</sys_updated_on>
            <sys_user/>
            <type/>
        </sys_ui_element>
        <sys_ui_element action="INSERT_OR_UPDATE">
            <element>.split</element>
            <position>3</position>
            <sys_created_by>admin</sys_created_by>
            <sys_created_on>2020-09-10 14:01:12</sys_created_on>
            <sys_id>559c916fa4c350107f44f6612a8fb680</sys_id>
            <sys_mod_count>0</sys_mod_count>
            <sys_ui_formatter/>
            <sys_ui_section caption="Statistics" display_value="Statistics" name="x_cdltd_loaner_req_loaner_request" sys_domain="global" view="d02a3041082300107f447452aafab96f">059c916fa4c350107f44f6612a8fb661</sys_ui_section>
            <sys_updated_by>admin</sys_updated_by>
            <sys_updated_on>2020-09-10 14:01:12</sys_updated_on>
            <sys_user/>
            <type>.split</type>
        </sys_ui_element>
        <sys_ui_element action="INSERT_OR_UPDATE">
            <element>opened_by</element>
            <position>4</position>
            <sys_created_by>admin</sys_created_by>
            <sys_created_on>2020-09-10 14:01:12</sys_created_on>
            <sys_id>d59c916fa4c350107f44f6612a8fb680</sys_id>
            <sys_mod_count>0</sys_mod_count>
            <sys_ui_formatter/>
            <sys_ui_section caption="Statistics" display_value="Statistics" name="x_cdltd_loaner_req_loaner_request" sys_domain="global" view="d02a3041082300107f447452aafab96f">059c916fa4c350107f44f6612a8fb661</sys_ui_section>
            <sys_updated_by>admin</sys_updated_by>
            <sys_updated_on>2020-09-10 14:01:12</sys_updated_on>
            <sys_user/>
            <type/>
        </sys_ui_element>
        <sys_ui_element action="INSERT_OR_UPDATE">
            <element>sys_updated_by</element>
            <position>5</position>
            <sys_created_by>admin</sys_created_by>
            <sys_created_on>2020-09-10 14:01:12</sys_created_on>
            <sys_id>599c916fa4c350107f44f6612a8fb680</sys_id>
            <sys_mod_count>0</sys_mod_count>
            <sys_ui_formatter/>
            <sys_ui_section caption="Statistics" display_value="Statistics" name="x_cdltd_loaner_req_loaner_request" sys_domain="global" view="d02a3041082300107f447452aafab96f">059c916fa4c350107f44f6612a8fb661</sys_ui_section>
            <sys_updated_by>admin</sys_updated_by>
            <sys_updated_on>2020-09-10 14:01:12</sys_updated_on>
            <sys_user/>
            <type/>
        </sys_ui_element>
        <sys_ui_element action="INSERT_OR_UPDATE">
            <element>closed_by</element>
            <position>6</position>
            <sys_created_by>admin</sys_created_by>
            <sys_created_on>2020-09-10 14:01:12</sys_created_on>
            <sys_id>d99c916fa4c350107f44f6612a8fb680</sys_id>
            <sys_mod_count>0</sys_mod_count>
            <sys_ui_formatter/>
            <sys_ui_section caption="Statistics" display_value="Statistics" name="x_cdltd_loaner_req_loaner_request" sys_domain="global" view="d02a3041082300107f447452aafab96f">059c916fa4c350107f44f6612a8fb661</sys_ui_section>
            <sys_updated_by>admin</sys_updated_by>
            <sys_updated_on>2020-09-10 14:01:12</sys_updated_on>
            <sys_user/>
            <type/>
        </sys_ui_element>
        <sys_ui_element action="INSERT_OR_UPDATE">
            <element>active</element>
            <position>7</position>
            <sys_created_by>admin</sys_created_by>
            <sys_created_on>2020-09-10 14:01:12</sys_created_on>
            <sys_id>5d9c916fa4c350107f44f6612a8fb680</sys_id>
            <sys_mod_count>0</sys_mod_count>
            <sys_ui_formatter/>
            <sys_ui_section caption="Statistics" display_value="Statistics" name="x_cdltd_loaner_req_loaner_request" sys_domain="global" view="d02a3041082300107f447452aafab96f">059c916fa4c350107f44f6612a8fb661</sys_ui_section>
            <sys_updated_by>admin</sys_updated_by>
            <sys_updated_on>2020-09-10 14:01:12</sys_updated_on>
            <sys_user/>
            <type/>
        </sys_ui_element>
        <sys_ui_section action="DELETE">
            <caption>Statistics</caption>
            <header>false</header>
            <name>x_cdltd_loaner_req_loaner_request</name>
            <roles/>
            <sys_class_name>sys_ui_section</sys_class_name>
            <sys_created_by>admin</sys_created_by>
            <sys_created_on>2020-09-10 14:01:11</sys_created_on>
            <sys_domain>global</sys_domain>
            <sys_domain_path>/</sys_domain_path>
            <sys_id>059c916fa4c350107f44f6612a8fb661</sys_id>
            <sys_mod_count>0</sys_mod_count>
            <sys_name>Statistics</sys_name>
            <sys_overrides/>
            <sys_package display_value="Loaner Request" source="x_cdltd_loaner_req">4bf62d9fa40f10107f44f6612a8fb6f7</sys_package>
            <sys_policy/>
            <sys_scope display_value="Loaner Request">4bf62d9fa40f10107f44f6612a8fb6f7</sys_scope>
            <sys_update_name>sys_ui_section_059c916fa4c350107f44f6612a8fb661</sys_update_name>
            <sys_updated_by>admin</sys_updated_by>
            <sys_updated_on>2020-09-10 14:01:11</sys_updated_on>
            <sys_user/>
            <title>false</title>
            <view display_value="Self Service" name="ess">d02a3041082300107f447452aafab96f</view>
            <view_name/>
        </sys_ui_section>
    </sys_ui_section>
    <sys_update_version action="INSERT_OR_UPDATE">
        <action>DELETE</action>
        <application display_value="Loaner Request">4bf62d9fa40f10107f44f6612a8fb6f7</application>
        <file_path/>
        <instance_id>7ea6e2ba1b835410158211b4bd4bcb57</instance_id>
        <instance_name>adf-sep-691-dev-012</instance_name>
        <name>sys_ui_section_059c916fa4c350107f44f6612a8fb661</name>
        <payload><![CDATA[<?xml version="1.0" encoding="UTF-8"?><record_update><sys_ui_section caption="Statistics" section_id="059c916fa4c350107f44f6612a8fb661" sys_domain="global" table="x_cdltd_loaner_req_loaner_request" version="3" view="ESS"><sys_ui_element action="INSERT_OR_UPDATE"><element>opened_at</element><position>0</position><sys_created_by>admin</sys_created_by><sys_created_on>2020-09-10 14:01:12</sys_created_on><sys_id>dd9c916fa4c350107f44f6612a8fb67f</sys_id><sys_mod_count>0</sys_mod_count><sys_ui_formatter/><sys_ui_section caption="Statistics" display_value="Statistics" name="x_cdltd_loaner_req_loaner_request" sys_domain="global" view="d02a3041082300107f447452aafab96f">059c916fa4c350107f44f6612a8fb661</sys_ui_section><sys_updated_by>admin</sys_updated_by><sys_updated_on>2020-09-10 14:01:12</sys_updated_on><sys_user/><type/></sys_ui_element><sys_ui_element action="INSERT_OR_UPDATE"><element>sys_updated_on</element><position>1</position><sys_created_by>admin</sys_created_by><sys_created_on>2020-09-10 14:01:12</sys_created_on><sys_id>519c916fa4c350107f44f6612a8fb680</sys_id><sys_mod_count>0</sys_mod_count><sys_ui_formatter/><sys_ui_section caption="Statistics" display_value="Statistics" name="x_cdltd_loaner_req_loaner_request" sys_domain="global" view="d02a3041082300107f447452aafab96f">059c916fa4c350107f44f6612a8fb661</sys_ui_section><sys_updated_by>admin</sys_updated_by><sys_updated_on>2020-09-10 14:01:12</sys_updated_on><sys_user/><type/></sys_ui_element><sys_ui_element action="INSERT_OR_UPDATE"><element>closed_at</element><position>2</position><sys_created_by>admin</sys_created_by><sys_created_on>2020-09-10 14:01:12</sys_created_on><sys_id>d19c916fa4c350107f44f6612a8fb680</sys_id><sys_mod_count>0</sys_mod_count><sys_ui_formatter/><sys_ui_section caption="Statistics" display_value="Statistics" name="x_cdltd_loaner_req_loaner_request" sys_domain="global" view="d02a3041082300107f447452aafab96f">059c916fa4c350107f44f6612a8fb661</sys_ui_section><sys_updated_by>admin</sys_updated_by><sys_updated_on>2020-09-10 14:01:12</sys_updated_on><sys_user/><type/></sys_ui_element><sys_ui_element action="INSERT_OR_UPDATE"><element>.split</element><position>3</position><sys_created_by>admin</sys_created_by><sys_created_on>2020-09-10 14:01:12</sys_created_on><sys_id>559c916fa4c350107f44f6612a8fb680</sys_id><sys_mod_count>0</sys_mod_count><sys_ui_formatter/><sys_ui_section caption="Statistics" display_value="Statistics" name="x_cdltd_loaner_req_loaner_request" sys_domain="global" view="d02a3041082300107f447452aafab96f">059c916fa4c350107f44f6612a8fb661</sys_ui_section><sys_updated_by>admin</sys_updated_by><sys_updated_on>2020-09-10 14:01:12</sys_updated_on><sys_user/><type>.split</type></sys_ui_element><sys_ui_element action="INSERT_OR_UPDATE"><element>opened_by</element><position>4</position><sys_created_by>admin</sys_created_by><sys_created_on>2020-09-10 14:01:12</sys_created_on><sys_id>d59c916fa4c350107f44f6612a8fb680</sys_id><sys_mod_count>0</sys_mod_count><sys_ui_formatter/><sys_ui_section caption="Statistics" display_value="Statistics" name="x_cdltd_loaner_req_loaner_request" sys_domain="global" view="d02a3041082300107f447452aafab96f">059c916fa4c350107f44f6612a8fb661</sys_ui_section><sys_updated_by>admin</sys_updated_by><sys_updated_on>2020-09-10 14:01:12</sys_updated_on><sys_user/><type/></sys_ui_element><sys_ui_element action="INSERT_OR_UPDATE"><element>sys_updated_by</element><position>5</position><sys_created_by>admin</sys_created_by><sys_created_on>2020-09-10 14:01:12</sys_created_on><sys_id>599c916fa4c350107f44f6612a8fb680</sys_id><sys_mod_count>0</sys_mod_count><sys_ui_formatter/><sys_ui_section caption="Statistics" display_value="Statistics" name="x_cdltd_loaner_req_loaner_request" sys_domain="global" view="d02a3041082300107f447452aafab96f">059c916fa4c350107f44f6612a8fb661</sys_ui_section><sys_updated_by>admin</sys_updated_by><sys_updated_on>2020-09-10 14:01:12</sys_updated_on><sys_user/><type/></sys_ui_element><sys_ui_element action="INSERT_OR_UPDATE"><element>closed_by</element><position>6</position><sys_created_by>admin</sys_created_by><sys_created_on>2020-09-10 14:01:12</sys_created_on><sys_id>d99c916fa4c350107f44f6612a8fb680</sys_id><sys_mod_count>0</sys_mod_count><sys_ui_formatter/><sys_ui_section caption="Statistics" display_value="Statistics" name="x_cdltd_loaner_req_loaner_request" sys_domain="global" view="d02a3041082300107f447452aafab96f">059c916fa4c350107f44f6612a8fb661</sys_ui_section><sys_updated_by>admin</sys_updated_by><sys_updated_on>2020-09-10 14:01:12</sys_updated_on><sys_user/><type/></sys_ui_element><sys_ui_element action="INSERT_OR_UPDATE"><element>active</element><position>7</position><sys_created_by>admin</sys_created_by><sys_created_on>2020-09-10 14:01:12</sys_created_on><sys_id>5d9c916fa4c350107f44f6612a8fb680</sys_id><sys_mod_count>0</sys_mod_count><sys_ui_formatter/><sys_ui_section caption="Statistics" display_value="Statistics" name="x_cdltd_loaner_req_loaner_request" sys_domain="global" view="d02a3041082300107f447452aafab96f">059c916fa4c350107f44f6612a8fb661</sys_ui_section><sys_updated_by>admin</sys_updated_by><sys_updated_on>2020-09-10 14:01:12</sys_updated_on><sys_user/><type/></sys_ui_element><sys_ui_section action="INSERT_OR_UPDATE"><caption>Statistics</caption><header>false</header><name>x_cdltd_loaner_req_loaner_request</name><roles/><sys_class_name>sys_ui_section</sys_class_name><sys_created_by>admin</sys_created_by><sys_created_on>2020-09-10 14:01:11</sys_created_on><sys_domain>global</sys_domain><sys_domain_path>/</sys_domain_path><sys_id>059c916fa4c350107f44f6612a8fb661</sys_id><sys_mod_count>0</sys_mod_count><sys_name>Statistics</sys_name><sys_overrides/><sys_package display_value="Loaner Request" source="x_cdltd_loaner_req">4bf62d9fa40f10107f44f6612a8fb6f7</sys_package><sys_policy/><sys_scope display_value="Loaner Request">4bf62d9fa40f10107f44f6612a8fb6f7</sys_scope><sys_update_name>sys_ui_section_059c916fa4c350107f44f6612a8fb661</sys_update_name><sys_updated_by>admin</sys_updated_by><sys_updated_on>2020-09-10 14:01:11</sys_updated_on><sys_user/><title>false</title><view display_value="Self Service" name="ess">d02a3041082300107f447452aafab96f</view><view_name/></sys_ui_section></sys_ui_section></record_update>]]></payload>
        <payload_hash>751946327</payload_hash>
        <record_name>Loaner Request</record_name>
        <reverted_from/>
        <source>ccc8e5dfa40f10107f44f6612a8fb660</source>
        <source_table>sys_update_set</source_table>
        <state>previous</state>
        <sys_created_by>admin</sys_created_by>
        <sys_created_on>2020-09-10 14:01:12</sys_created_on>
        <sys_id>599c916fa4c350107f44f6612a8fb682</sys_id>
        <sys_mod_count>0</sys_mod_count>
        <sys_recorded_at>1747851f90a0000001</sys_recorded_at>
        <sys_updated_by>admin</sys_updated_by>
        <sys_updated_on>2020-09-10 14:01:12</sys_updated_on>
        <type>Form Layout</type>
        <update_guid>d19c916f8ac3501090add27f58d24682</update_guid>
        <update_guid_history>d19c916f8ac3501090add27f58d24682:751946327</update_guid_history>
    </sys_update_version>
    <sys_metadata_delete action="INSERT_OR_UPDATE">
        <sys_audit_delete/>
        <sys_class_name>sys_metadata_delete</sys_class_name>
        <sys_created_by>admin</sys_created_by>
        <sys_created_on>2020-09-10 14:01:56</sys_created_on>
        <sys_db_object display_value="" name="sys_ui_section">sys_ui_section</sys_db_object>
        <sys_id>3cff48fc71654a61ac4dbdd521522241</sys_id>
        <sys_metadata>059c916fa4c350107f44f6612a8fb661</sys_metadata>
        <sys_mod_count>0</sys_mod_count>
        <sys_name>Statistics</sys_name>
        <sys_package display_value="Loaner Request" source="x_cdltd_loaner_req">4bf62d9fa40f10107f44f6612a8fb6f7</sys_package>
        <sys_parent display_value="Loaner Request">fb6725dfa40f10107f44f6612a8fb63a</sys_parent>
        <sys_policy/>
        <sys_scope display_value="Loaner Request">4bf62d9fa40f10107f44f6612a8fb6f7</sys_scope>
        <sys_scope_delete display_value="">8df6cab8e6984c788b040bcc9b15b664</sys_scope_delete>
        <sys_update_name>sys_ui_section_059c916fa4c350107f44f6612a8fb661</sys_update_name>
        <sys_update_version display_value="sys_ui_section_059c916fa4c350107f44f6612a8fb661">599c916fa4c350107f44f6612a8fb682</sys_update_version>
        <sys_updated_by>admin</sys_updated_by>
        <sys_updated_on>2020-09-10 14:01:56</sys_updated_on>
    </sys_metadata_delete>
</record_update>
